{
    "anims": {}, 
    "box": [
        -1.879878044128418, 
        -0.003410999896004796, 
        -1.8050739765167236, 
        1.7300759553909302, 
        7.715518951416016, 
        1.804880976676941
    ], 
    "custom": true, 
    "graph": "", 
    "materials": [
        "custom_model/134282838/Material_422004"
    ], 
    "meshes": [
        "custom_model/134282838/422004"
    ], 
    "model_id": 134282838, 
    "name": "\u6b66\u5668\u5927\u5e08", 
    "physics_meshes": [
        "custom_model/134282838/AutoPhy_Mesh_422004"
    ], 
    "preview_icon": "UP1ModelPreview/134282838", 
    "skeleton": "", 
    "textures": []
}