<?xml version="1.0" encoding="utf-8"?>
<Resource>
	<Version>8</Version>
	<SRenderMeshData>
		<Root>
			<Sub/>
			<Entity type="SRenderMeshData">
				<VertexFormat count="4">
					<Element index="0">P3F_N4B_T2F</Element>
					<Element index="1">None</Element>
					<Element index="2">None</Element>
					<Element index="3">None</Element>
				</VertexFormat>
				<VertexCount>528</VertexCount>
				<IndexCount>768</IndexCount>
				<StreamingMask>0</StreamingMask>
				<PrimTopology>Tri_List</PrimTopology>
				<KeepData>false</KeepData>
				<BoundingVolume rawdata="AAAAMwAAgLMAAICzEDcGPyPAIj8RNwY/I8CiPw==">(2.9802322387695312e-08,-5.9604644775390625e-08,-5.9604644775390625e-08,0.52427768707275391,0.63574427366256714,0.52427774667739868,1.2714885473251343)</BoundingVolume>
				<BoundingBox rawdata="EDcGvyTAIr8SNwa/ETcGPyLAIj8QNwY/">(-0.52427768707275391,-0.63574433326721191,-0.52427780628204346,0.52427774667739868,0.63574421405792236,0.52427768707275391)</BoundingBox>
				<Streams count="4">
					<Element index="0">
						<StreamSize>12672</StreamSize>
					</Element>
					<Element index="1">
						<StreamSize>0</StreamSize>
					</Element>
					<Element index="2">
						<StreamSize>0</StreamSize>
					</Element>
					<Element index="3">
						<StreamSize>0</StreamSize>
					</Element>
				</Streams>
				<Indices>
					<StreamSize>1536</StreamSize>
				</Indices>
				<Groups count="1" ordered="true">
					<Element index="0">
						<StartIndex>0</StartIndex>
						<IndicesCount>768</IndicesCount>
						<StartVertex>0</StartVertex>
						<VerticesCount>528</VerticesCount>
						<BoundingVolume rawdata="AAAAMwAAgLMAAICzEDcGPyPAIj8RNwY/I8CiPw==">(2.9802322387695312e-08,-5.9604644775390625e-08,-5.9604644775390625e-08,0.52427768707275391,0.63574427366256714,0.52427774667739868,1.2714885473251343)</BoundingVolume>
						<BoundingBox rawdata="EDcGvyTAIr8SNwa/ETcGPyLAIj8QNwY/">(-0.52427768707275391,-0.63574433326721191,-0.52427780628204346,0.52427774667739868,0.63574421405792236,0.52427768707275391)</BoundingBox>
					</Element>
				</Groups>
			</Entity>
		</Root>
	</SRenderMeshData>
</Resource>
