{
    "data": {
        "adapter_option": [
            false, 
            false, 
            false, 
            false, 
            0, 
            0, 
            0, 
            0
        ], 
        "anchor": {
            "__tuple__": true, 
            "items": [
                0.5, 
                0.5
            ]
        }, 
        "can_drag": false, 
        "children": [
            {
                "adapter_option": [
                    true, 
                    true, 
                    true, 
                    true, 
                    0.0, 
                    0.0, 
                    0.0, 
                    0.0
                ], 
                "anchor": {
                    "__tuple__": true, 
                    "items": [
                        0.5, 
                        0.5
                    ]
                }, 
                "can_drag": false, 
                "cap_insets": {
                    "__tuple__": true, 
                    "items": [
                        372.0, 
                        20.0, 
                        372.0, 
                        20.0
                    ]
                }, 
                "children": [], 
                "color": {
                    "__tuple__": true, 
                    "items": [
                        255, 
                        255, 
                        255, 
                        255
                    ]
                }, 
                "comp_type": "Image", 
                "event_list": [], 
                "hover_child": "", 
                "image": 134238673, 
                "is_scale9_enable": false, 
                "name": "bg", 
                "opacity": 1.0, 
                "open_adapter": true, 
                "pos_data": {
                    "__tuple__": true, 
                    "items": [
                        558.0, 
                        29.0, 
                        50.0, 
                        50.0, 
                        0, 
                        0
                    ]
                }, 
                "prefab_sub_key": "4b4c3006-370a-4652-a886-df990220c9b4", 
                "rotation": 0, 
                "scale": {
                    "__tuple__": true, 
                    "items": [
                        1, 
                        1
                    ]
                }, 
                "scene_ui_name": null, 
                "size": {
                    "__tuple__": true, 
                    "items": [
                        1116.0, 
                        58.0
                    ]
                }, 
                "size_adaptive": false, 
                "swallow_touches": false, 
                "type": 4, 
                "visible": true
            }, 
            {
                "adapter_option": [
                    false, 
                    false, 
                    true, 
                    false, 
                    3.0, 
                    3.0, 
                    100.0, 
                    966.0
                ], 
                "anchor": {
                    "__tuple__": true, 
                    "items": [
                        0.5, 
                        0.5
                    ]
                }, 
                "can_drag": false, 
                "children": [
                    {
                        "adapter_option": [
                            true, 
                            true, 
                            true, 
                            true, 
                            0.0, 
                            0.0, 
                            0.0, 
                            0.0
                        ], 
                        "anchor": {
                            "__tuple__": true, 
                            "items": [
                                0.5, 
                                0.5
                            ]
                        }, 
                        "can_drag": false, 
                        "cap_insets": {
                            "__tuple__": true, 
                            "items": [
                                17.0, 
                                17.0, 
                                17.0, 
                                17.0
                            ]
                        }, 
                        "children": [], 
                        "color": {
                            "__tuple__": true, 
                            "items": [
                                255, 
                                255, 
                                255, 
                                255
                            ]
                        }, 
                        "comp_type": "Image", 
                        "event_list": [], 
                        "hover_child": "", 
                        "image": 134228335, 
                        "is_scale9_enable": false, 
                        "name": "bg", 
                        "opacity": 1.0, 
                        "open_adapter": true, 
                        "pos_data": {
                            "__tuple__": true, 
                            "items": [
                                25.0, 
                                26.0, 
                                50.0, 
                                50.0, 
                                0, 
                                0
                            ]
                        }, 
                        "prefab_sub_key": "ec50ea35-8c53-4b4b-a296-843a34d2bc22", 
                        "rotation": 0, 
                        "scale": {
                            "__tuple__": true, 
                            "items": [
                                1, 
                                1
                            ]
                        }, 
                        "scene_ui_name": null, 
                        "size": {
                            "__tuple__": true, 
                            "items": [
                                50.0, 
                                52.0
                            ]
                        }, 
                        "size_adaptive": false, 
                        "swallow_touches": false, 
                        "type": 4, 
                        "visible": true
                    }, 
                    {
                        "adapter_option": [
                            true, 
                            true, 
                            true, 
                            true, 
                            0.0, 
                            0.0, 
                            0.0, 
                            0.0
                        ], 
                        "alignment": {
                            "__tuple__": true, 
                            "items": [
                                2, 
                                8
                            ]
                        }, 
                        "anchor": {
                            "__tuple__": true, 
                            "items": [
                                0.5, 
                                0.5
                            ]
                        }, 
                        "bold": false, 
                        "border": true, 
                        "can_drag": false, 
                        "children": [], 
                        "comp_type": "TextLabel", 
                        "event_list": [], 
                        "font": {
                            "__tuple__": true, 
                            "items": [
                                "134239387", 
                                20
                            ]
                        }, 
                        "font_color": [
                            189, 
                            189, 
                            189, 
                            255
                        ], 
                        "font_min_size": 36, 
                        "gradient": false, 
                        "gradient_bl_color": {
                            "__tuple__": true, 
                            "items": [
                                255, 
                                255, 
                                255, 
                                255
                            ]
                        }, 
                        "gradient_br_color": {
                            "__tuple__": true, 
                            "items": [
                                255, 
                                255, 
                                255, 
                                255
                            ]
                        }, 
                        "gradient_tl_color": {
                            "__tuple__": true, 
                            "items": [
                                255, 
                                255, 
                                255, 
                                255
                            ]
                        }, 
                        "gradient_tr_color": {
                            "__tuple__": true, 
                            "items": [
                                255, 
                                255, 
                                255, 
                                255
                            ]
                        }, 
                        "hover_child": "", 
                        "italics": false, 
                        "label_effect": {
                            "__tuple__": true, 
                            "items": [
                                false, 
                                false, 
                                false, 
                                false, 
                                true, 
                                false
                            ]
                        }, 
                        "line_space": {
                            "__tuple__": true, 
                            "items": [
                                0, 
                                0
                            ]
                        }, 
                        "name": "_rank_TEXT", 
                        "opacity": 1.0, 
                        "open_adapter": true, 
                        "over_pattern": false, 
                        "pos_data": {
                            "__tuple__": true, 
                            "items": [
                                25.0, 
                                26.0, 
                                50.0, 
                                50.0, 
                                0, 
                                0
                            ]
                        }, 
                        "prefab_sub_key": "3b771be5-b40f-4ae8-95c5-ef47dffea616", 
                        "rotation": 0, 
                        "scale": {
                            "__tuple__": true, 
                            "items": [
                                1, 
                                1
                            ]
                        }, 
                        "scene_ui_name": null, 
                        "shadow": false, 
                        "size": {
                            "__tuple__": true, 
                            "items": [
                                50.0, 
                                52.0
                            ]
                        }, 
                        "strike_through": false, 
                        "strike_through_color": {
                            "__tuple__": true, 
                            "items": [
                                0, 
                                0, 
                                0, 
                                255
                            ]
                        }, 
                        "strike_through_size": 0, 
                        "swallow_touches": false, 
                        "text": {
                            "__tuple__": true, 
                            "items": [
                                "999", 
                                true
                            ]
                        }, 
                        "text_bind": {
                            "__tuple__": true, 
                            "items": [
                                null, 
                                null
                            ]
                        }, 
                        "text_border_color": {
                            "__tuple__": true, 
                            "items": [
                                0, 
                                0, 
                                0, 
                                255
                            ]
                        }, 
                        "text_border_width": 2, 
                        "text_format": "", 
                        "text_italic_radius": 0.5, 
                        "text_shadow_color": {
                            "__tuple__": true, 
                            "items": [
                                123, 
                                123, 
                                123, 
                                255
                            ]
                        }, 
                        "text_shadow_offset": {
                            "__tuple__": true, 
                            "items": [
                                0, 
                                0
                            ]
                        }, 
                        "type": 3, 
                        "typewriter_effect": 0, 
                        "typewriter_space": 0, 
                        "under_line": false, 
                        "visible": true
                    }, 
                    {
                        "adapter_option": [
                            true, 
                            true, 
                            true, 
                            true, 
                            -10.0, 
                            -10.0, 
                            -13.0, 
                            -13.0
                        ], 
                        "anchor": {
                            "__tuple__": true, 
                            "items": [
                                0.5, 
                                0.5
                            ]
                        }, 
                        "can_drag": false, 
                        "cap_insets": {
                            "__tuple__": true, 
                            "items": [
                                25.0, 
                                24.0, 
                                25.0, 
                                24.0
                            ]
                        }, 
                        "children": [], 
                        "color": {
                            "__tuple__": true, 
                            "items": [
                                255, 
                                255, 
                                255, 
                                255
                            ]
                        }, 
                        "comp_type": "Image", 
                        "event_list": [], 
                        "hover_child": "", 
                        "image": 134267716, 
                        "is_scale9_enable": false, 
                        "name": "bg_top", 
                        "opacity": 1.0, 
                        "open_adapter": true, 
                        "pos_data": {
                            "__tuple__": true, 
                            "items": [
                                25.0, 
                                26.0, 
                                50.0, 
                                50.0, 
                                0, 
                                0
                            ]
                        }, 
                        "prefab_sub_key": "bfe22ca0-ffbf-4702-a178-ac200d83d0a2", 
                        "rotation": 0, 
                        "scale": {
                            "__tuple__": true, 
                            "items": [
                                1, 
                                1
                            ]
                        }, 
                        "scene_ui_name": null, 
                        "size": {
                            "__tuple__": true, 
                            "items": [
                                76.0, 
                                72.0
                            ]
                        }, 
                        "size_adaptive": false, 
                        "swallow_touches": false, 
                        "type": 4, 
                        "visible": false
                    }, 
                    {
                        "adapter_option": [
                            true, 
                            true, 
                            true, 
                            true, 
                            -8.0, 
                            -8.0, 
                            -10.0, 
                            -10.0
                        ], 
                        "anchor": {
                            "__tuple__": true, 
                            "items": [
                                0.5, 
                                0.5
                            ]
                        }, 
                        "can_drag": false, 
                        "cap_insets": {
                            "__tuple__": true, 
                            "items": [
                                24.0, 
                                22.0, 
                                24.0, 
                                22.0
                            ]
                        }, 
                        "children": [], 
                        "color": {
                            "__tuple__": true, 
                            "items": [
                                255, 
                                255, 
                                255, 
                                255
                            ]
                        }, 
                        "comp_type": "Image", 
                        "event_list": [], 
                        "hover_child": "", 
                        "image": 134250862, 
                        "is_scale9_enable": false, 
                        "name": "bg_top_2", 
                        "opacity": 1.0, 
                        "open_adapter": true, 
                        "pos_data": {
                            "__tuple__": true, 
                            "items": [
                                25.0, 
                                26.0, 
                                50.0, 
                                50.0, 
                                0, 
                                0
                            ]
                        }, 
                        "prefab_sub_key": "86302096-c56d-43dc-8549-a01094c67a87", 
                        "rotation": 0, 
                        "scale": {
                            "__tuple__": true, 
                            "items": [
                                1, 
                                1
                            ]
                        }, 
                        "scene_ui_name": null, 
                        "size": {
                            "__tuple__": true, 
                            "items": [
                                70.0, 
                                68.0
                            ]
                        }, 
                        "size_adaptive": false, 
                        "swallow_touches": false, 
                        "type": 4, 
                        "visible": false
                    }, 
                    {
                        "adapter_option": [
                            true, 
                            true, 
                            true, 
                            true, 
                            -6.0, 
                            -6.0, 
                            -6.0, 
                            -6.0
                        ], 
                        "anchor": {
                            "__tuple__": true, 
                            "items": [
                                0.5, 
                                0.5
                            ]
                        }, 
                        "can_drag": false, 
                        "cap_insets": {
                            "__tuple__": true, 
                            "items": [
                                21.0, 
                                21.0, 
                                21.0, 
                                21.0
                            ]
                        }, 
                        "children": [], 
                        "color": {
                            "__tuple__": true, 
                            "items": [
                                255, 
                                255, 
                                255, 
                                255
                            ]
                        }, 
                        "comp_type": "Image", 
                        "event_list": [], 
                        "hover_child": "", 
                        "image": 134227199, 
                        "is_scale9_enable": false, 
                        "name": "bg_top_3", 
                        "opacity": 1.0, 
                        "open_adapter": true, 
                        "pos_data": {
                            "__tuple__": true, 
                            "items": [
                                25.0, 
                                26.0, 
                                50.0, 
                                50.0, 
                                0, 
                                0
                            ]
                        }, 
                        "prefab_sub_key": "18e7bd36-71b8-4de9-bbe3-801f73c1fc18", 
                        "rotation": 0, 
                        "scale": {
                            "__tuple__": true, 
                            "items": [
                                1, 
                                1
                            ]
                        }, 
                        "scene_ui_name": null, 
                        "size": {
                            "__tuple__": true, 
                            "items": [
                                62.0, 
                                64.0
                            ]
                        }, 
                        "size_adaptive": false, 
                        "swallow_touches": false, 
                        "type": 4, 
                        "visible": false
                    }
                ], 
                "clip_enabled": false, 
                "clipping_type": 1, 
                "color": {
                    "__tuple__": true, 
                    "items": [
                        255, 
                        255, 
                        255, 
                        0
                    ]
                }, 
                "comp_type": "Layout", 
                "event_list": [], 
                "hover_child": "", 
                "mask_image": 999, 
                "name": "rank", 
                "opacity": 1.0, 
                "open_adapter": true, 
                "pos_data": {
                    "__tuple__": true, 
                    "items": [
                        125.0, 
                        29.0, 
                        11.2007, 
                        50.0, 
                        0, 
                        0
                    ]
                }, 
                "prefab_sub_key": "fe8e2075-34ad-4afc-800f-d46500c3b9d4", 
                "rotation": 0, 
                "scale": {
                    "__tuple__": true, 
                    "items": [
                        1, 
                        1
                    ]
                }, 
                "scene_ui_name": null, 
                "size": {
                    "__tuple__": true, 
                    "items": [
                        50.0, 
                        52.0
                    ]
                }, 
                "swallow_touches": false, 
                "type": 7, 
                "visible": true
            }, 
            {
                "adapter_option": [
                    true, 
                    true, 
                    true, 
                    false, 
                    0.0, 
                    0.0, 
                    300.0, 
                    516.0
                ], 
                "anchor": {
                    "__tuple__": true, 
                    "items": [
                        0.5, 
                        0.5
                    ]
                }, 
                "can_drag": false, 
                "children": [
                    {
                        "adapter_option": [
                            true, 
                            true, 
                            true, 
                            true, 
                            0.0, 
                            0.0, 
                            0.0, 
                            0.0
                        ], 
                        "alignment": {
                            "__tuple__": true, 
                            "items": [
                                2, 
                                8
                            ]
                        }, 
                        "anchor": {
                            "__tuple__": true, 
                            "items": [
                                0.5, 
                                0.5
                            ]
                        }, 
                        "bold": false, 
                        "border": true, 
                        "can_drag": false, 
                        "children": [], 
                        "comp_type": "TextLabel", 
                        "event_list": [], 
                        "font": {
                            "__tuple__": true, 
                            "items": [
                                "134239387", 
                                20
                            ]
                        }, 
                        "font_color": [
                            189, 
                            189, 
                            189, 
                            255
                        ], 
                        "font_min_size": 36, 
                        "gradient": false, 
                        "gradient_bl_color": {
                            "__tuple__": true, 
                            "items": [
                                255, 
                                255, 
                                255, 
                                255
                            ]
                        }, 
                        "gradient_br_color": {
                            "__tuple__": true, 
                            "items": [
                                255, 
                                255, 
                                255, 
                                255
                            ]
                        }, 
                        "gradient_tl_color": {
                            "__tuple__": true, 
                            "items": [
                                255, 
                                255, 
                                255, 
                                255
                            ]
                        }, 
                        "gradient_tr_color": {
                            "__tuple__": true, 
                            "items": [
                                255, 
                                255, 
                                255, 
                                255
                            ]
                        }, 
                        "hover_child": "", 
                        "italics": false, 
                        "label_effect": {
                            "__tuple__": true, 
                            "items": [
                                false, 
                                false, 
                                false, 
                                false, 
                                true, 
                                false
                            ]
                        }, 
                        "line_space": {
                            "__tuple__": true, 
                            "items": [
                                0, 
                                0
                            ]
                        }, 
                        "name": "_player_plat_name_TEXT", 
                        "opacity": 1.0, 
                        "open_adapter": true, 
                        "over_pattern": false, 
                        "pos_data": {
                            "__tuple__": true, 
                            "items": [
                                150.0, 
                                29.0, 
                                50.0, 
                                50.0, 
                                0, 
                                0
                            ]
                        }, 
                        "prefab_sub_key": "97ea337b-1e40-44b5-92d2-6fbe93625a11", 
                        "rotation": 0, 
                        "scale": {
                            "__tuple__": true, 
                            "items": [
                                1, 
                                1
                            ]
                        }, 
                        "scene_ui_name": null, 
                        "shadow": false, 
                        "size": {
                            "__tuple__": true, 
                            "items": [
                                300.0, 
                                58.0
                            ]
                        }, 
                        "strike_through": false, 
                        "strike_through_color": {
                            "__tuple__": true, 
                            "items": [
                                0, 
                                0, 
                                0, 
                                255
                            ]
                        }, 
                        "strike_through_size": 0, 
                        "swallow_touches": false, 
                        "text": {
                            "__tuple__": true, 
                            "items": [
                                "\u73a9\u5bb6\u540d\u5b57\u4e03\u4e2a\u5b57#8888", 
                                true
                            ]
                        }, 
                        "text_bind": {
                            "__tuple__": true, 
                            "items": [
                                null, 
                                null
                            ]
                        }, 
                        "text_border_color": {
                            "__tuple__": true, 
                            "items": [
                                0, 
                                0, 
                                0, 
                                255
                            ]
                        }, 
                        "text_border_width": 2, 
                        "text_format": "", 
                        "text_italic_radius": 0.5, 
                        "text_shadow_color": {
                            "__tuple__": true, 
                            "items": [
                                123, 
                                123, 
                                123, 
                                255
                            ]
                        }, 
                        "text_shadow_offset": {
                            "__tuple__": true, 
                            "items": [
                                0, 
                                0
                            ]
                        }, 
                        "type": 3, 
                        "typewriter_effect": 0, 
                        "typewriter_space": 0, 
                        "under_line": false, 
                        "visible": true
                    }
                ], 
                "clip_enabled": false, 
                "clipping_type": 1, 
                "color": {
                    "__tuple__": true, 
                    "items": [
                        255, 
                        255, 
                        255, 
                        0
                    ]
                }, 
                "comp_type": "Layout", 
                "event_list": [], 
                "hover_child": "", 
                "mask_image": 999, 
                "name": "player_plat_name", 
                "opacity": 1.0, 
                "open_adapter": true, 
                "pos_data": {
                    "__tuple__": true, 
                    "items": [
                        450.0, 
                        29.0, 
                        40.3226, 
                        50.0, 
                        0, 
                        0
                    ]
                }, 
                "prefab_sub_key": "4f95ae29-74a0-4574-a709-bf1e54b2d7d5", 
                "rotation": 0, 
                "scale": {
                    "__tuple__": true, 
                    "items": [
                        1, 
                        1
                    ]
                }, 
                "scene_ui_name": null, 
                "size": {
                    "__tuple__": true, 
                    "items": [
                        300.0, 
                        58.0
                    ]
                }, 
                "swallow_touches": false, 
                "type": 7, 
                "visible": true
            }, 
            {
                "adapter_option": [
                    true, 
                    true, 
                    true, 
                    false, 
                    0.0, 
                    0.0, 
                    600.0, 
                    216.0
                ], 
                "anchor": {
                    "__tuple__": true, 
                    "items": [
                        0.5, 
                        0.5
                    ]
                }, 
                "can_drag": false, 
                "children": [
                    {
                        "adapter_option": [
                            true, 
                            true, 
                            true, 
                            true, 
                            0.0, 
                            0.0, 
                            0.0, 
                            0.0
                        ], 
                        "alignment": {
                            "__tuple__": true, 
                            "items": [
                                2, 
                                8
                            ]
                        }, 
                        "anchor": {
                            "__tuple__": true, 
                            "items": [
                                0.5, 
                                0.5
                            ]
                        }, 
                        "bold": false, 
                        "border": true, 
                        "can_drag": false, 
                        "children": [], 
                        "comp_type": "TextLabel", 
                        "event_list": [], 
                        "font": {
                            "__tuple__": true, 
                            "items": [
                                "134239387", 
                                20
                            ]
                        }, 
                        "font_color": [
                            189, 
                            189, 
                            189, 
                            255
                        ], 
                        "font_min_size": 36, 
                        "gradient": false, 
                        "gradient_bl_color": {
                            "__tuple__": true, 
                            "items": [
                                255, 
                                255, 
                                255, 
                                255
                            ]
                        }, 
                        "gradient_br_color": {
                            "__tuple__": true, 
                            "items": [
                                255, 
                                255, 
                                255, 
                                255
                            ]
                        }, 
                        "gradient_tl_color": {
                            "__tuple__": true, 
                            "items": [
                                255, 
                                255, 
                                255, 
                                255
                            ]
                        }, 
                        "gradient_tr_color": {
                            "__tuple__": true, 
                            "items": [
                                255, 
                                255, 
                                255, 
                                255
                            ]
                        }, 
                        "hover_child": "", 
                        "italics": false, 
                        "label_effect": {
                            "__tuple__": true, 
                            "items": [
                                false, 
                                false, 
                                false, 
                                false, 
                                true, 
                                false
                            ]
                        }, 
                        "line_space": {
                            "__tuple__": true, 
                            "items": [
                                0, 
                                0
                            ]
                        }, 
                        "name": "_rank_value_TEXT", 
                        "opacity": 1.0, 
                        "open_adapter": true, 
                        "over_pattern": false, 
                        "pos_data": {
                            "__tuple__": true, 
                            "items": [
                                150.0, 
                                29.0, 
                                50.0, 
                                50.0, 
                                0, 
                                0
                            ]
                        }, 
                        "prefab_sub_key": "792301ee-7ddc-4560-b33b-ceb6b149b312", 
                        "rotation": 0, 
                        "scale": {
                            "__tuple__": true, 
                            "items": [
                                1, 
                                1
                            ]
                        }, 
                        "scene_ui_name": null, 
                        "shadow": false, 
                        "size": {
                            "__tuple__": true, 
                            "items": [
                                300.0, 
                                58.0
                            ]
                        }, 
                        "strike_through": false, 
                        "strike_through_color": {
                            "__tuple__": true, 
                            "items": [
                                0, 
                                0, 
                                0, 
                                255
                            ]
                        }, 
                        "strike_through_size": 0, 
                        "swallow_touches": false, 
                        "text": {
                            "__tuple__": true, 
                            "items": [
                                "88888888", 
                                true
                            ]
                        }, 
                        "text_bind": {
                            "__tuple__": true, 
                            "items": [
                                null, 
                                null
                            ]
                        }, 
                        "text_border_color": {
                            "__tuple__": true, 
                            "items": [
                                0, 
                                0, 
                                0, 
                                255
                            ]
                        }, 
                        "text_border_width": 2, 
                        "text_format": "", 
                        "text_italic_radius": 0.5, 
                        "text_shadow_color": {
                            "__tuple__": true, 
                            "items": [
                                123, 
                                123, 
                                123, 
                                255
                            ]
                        }, 
                        "text_shadow_offset": {
                            "__tuple__": true, 
                            "items": [
                                0, 
                                0
                            ]
                        }, 
                        "type": 3, 
                        "typewriter_effect": 0, 
                        "typewriter_space": 0, 
                        "under_line": false, 
                        "visible": true
                    }
                ], 
                "clip_enabled": false, 
                "clipping_type": 1, 
                "color": {
                    "__tuple__": true, 
                    "items": [
                        255, 
                        255, 
                        255, 
                        0
                    ]
                }, 
                "comp_type": "Layout", 
                "event_list": [], 
                "hover_child": "", 
                "mask_image": 999, 
                "name": "rank_value", 
                "opacity": 1.0, 
                "open_adapter": true, 
                "pos_data": {
                    "__tuple__": true, 
                    "items": [
                        750.0, 
                        29.0, 
                        67.2043, 
                        50.0, 
                        0, 
                        0
                    ]
                }, 
                "prefab_sub_key": "e47e6296-f9bd-43aa-aded-a4a5ff9e3703", 
                "rotation": 0, 
                "scale": {
                    "__tuple__": true, 
                    "items": [
                        1, 
                        1
                    ]
                }, 
                "scene_ui_name": null, 
                "size": {
                    "__tuple__": true, 
                    "items": [
                        300.0, 
                        58.0
                    ]
                }, 
                "swallow_touches": false, 
                "type": 7, 
                "visible": true
            }, 
            {
                "adapter_option": [
                    true, 
                    true, 
                    true, 
                    true, 
                    0.0, 
                    0.0, 
                    900.0, 
                    0.0
                ], 
                "anchor": {
                    "__tuple__": true, 
                    "items": [
                        0.5, 
                        0.5
                    ]
                }, 
                "can_drag": false, 
                "children": [
                    {
                        "adapter_option": [
                            true, 
                            true, 
                            true, 
                            true, 
                            0.0, 
                            0.0, 
                            0.0, 
                            0.0
                        ], 
                        "alignment": {
                            "__tuple__": true, 
                            "items": [
                                2, 
                                8
                            ]
                        }, 
                        "anchor": {
                            "__tuple__": true, 
                            "items": [
                                0.5, 
                                0.5
                            ]
                        }, 
                        "bold": false, 
                        "border": true, 
                        "can_drag": false, 
                        "children": [], 
                        "comp_type": "TextLabel", 
                        "event_list": [], 
                        "font": {
                            "__tuple__": true, 
                            "items": [
                                "134239387", 
                                18
                            ]
                        }, 
                        "font_color": [
                            189, 
                            189, 
                            189, 
                            255
                        ], 
                        "font_min_size": 36, 
                        "gradient": false, 
                        "gradient_bl_color": {
                            "__tuple__": true, 
                            "items": [
                                255, 
                                255, 
                                255, 
                                255
                            ]
                        }, 
                        "gradient_br_color": {
                            "__tuple__": true, 
                            "items": [
                                255, 
                                255, 
                                255, 
                                255
                            ]
                        }, 
                        "gradient_tl_color": {
                            "__tuple__": true, 
                            "items": [
                                255, 
                                255, 
                                255, 
                                255
                            ]
                        }, 
                        "gradient_tr_color": {
                            "__tuple__": true, 
                            "items": [
                                255, 
                                255, 
                                255, 
                                255
                            ]
                        }, 
                        "hover_child": "", 
                        "italics": false, 
                        "label_effect": {
                            "__tuple__": true, 
                            "items": [
                                false, 
                                false, 
                                false, 
                                false, 
                                true, 
                                false
                            ]
                        }, 
                        "line_space": {
                            "__tuple__": true, 
                            "items": [
                                0, 
                                0
                            ]
                        }, 
                        "name": "_add_info_TEXT", 
                        "opacity": 1.0, 
                        "open_adapter": true, 
                        "over_pattern": false, 
                        "pos_data": {
                            "__tuple__": true, 
                            "items": [
                                108.0, 
                                29.0, 
                                50.0, 
                                50.0, 
                                0, 
                                0
                            ]
                        }, 
                        "prefab_sub_key": "fa137002-d171-41a3-b85b-03c871162ffb", 
                        "rotation": 0, 
                        "scale": {
                            "__tuple__": true, 
                            "items": [
                                1, 
                                1
                            ]
                        }, 
                        "scene_ui_name": null, 
                        "shadow": false, 
                        "size": {
                            "__tuple__": true, 
                            "items": [
                                216.0, 
                                58.0
                            ]
                        }, 
                        "strike_through": false, 
                        "strike_through_color": {
                            "__tuple__": true, 
                            "items": [
                                0, 
                                0, 
                                0, 
                                255
                            ]
                        }, 
                        "strike_through_size": 0, 
                        "swallow_touches": false, 
                        "text": {
                            "__tuple__": true, 
                            "items": [
                                "2024/09/05/22:28:00", 
                                true
                            ]
                        }, 
                        "text_bind": {
                            "__tuple__": true, 
                            "items": [
                                null, 
                                null
                            ]
                        }, 
                        "text_border_color": {
                            "__tuple__": true, 
                            "items": [
                                0, 
                                0, 
                                0, 
                                255
                            ]
                        }, 
                        "text_border_width": 2, 
                        "text_format": "", 
                        "text_italic_radius": 0.5, 
                        "text_shadow_color": {
                            "__tuple__": true, 
                            "items": [
                                123, 
                                123, 
                                123, 
                                255
                            ]
                        }, 
                        "text_shadow_offset": {
                            "__tuple__": true, 
                            "items": [
                                0, 
                                0
                            ]
                        }, 
                        "type": 3, 
                        "typewriter_effect": 0, 
                        "typewriter_space": 0, 
                        "under_line": false, 
                        "visible": true
                    }
                ], 
                "clip_enabled": false, 
                "clipping_type": 1, 
                "color": {
                    "__tuple__": true, 
                    "items": [
                        255, 
                        255, 
                        255, 
                        0
                    ]
                }, 
                "comp_type": "Layout", 
                "event_list": [], 
                "hover_child": "", 
                "mask_image": 999, 
                "name": "add_info", 
                "opacity": 1.0, 
                "open_adapter": true, 
                "pos_data": {
                    "__tuple__": true, 
                    "items": [
                        1008.0, 
                        29.0, 
                        90.3226, 
                        50.0, 
                        0, 
                        0
                    ]
                }, 
                "prefab_sub_key": "6bafce0c-4654-4c6c-979f-01fd480b445b", 
                "rotation": 0, 
                "scale": {
                    "__tuple__": true, 
                    "items": [
                        1, 
                        1
                    ]
                }, 
                "scene_ui_name": null, 
                "size": {
                    "__tuple__": true, 
                    "items": [
                        216.0, 
                        58.0
                    ]
                }, 
                "swallow_touches": false, 
                "type": 7, 
                "visible": true
            }
        ], 
        "clip_enabled": false, 
        "clipping_type": 1, 
        "color": {
            "__tuple__": true, 
            "items": [
                255, 
                255, 
                255, 
                0
            ]
        }, 
        "comp_type": "Layout", 
        "custom_kv": {}, 
        "event_list": [], 
        "hover_child": "", 
        "mask_image": 999, 
        "name": "slot_main_rank", 
        "opacity": 1.0, 
        "open_adapter": false, 
        "pos_data": {
            "__tuple__": true, 
            "items": [
                960.0, 
                540.0, 
                50.0, 
                50.0, 
                1, 
                1
            ]
        }, 
        "prefab_key": "0823f4a4-d176-4dae-bb4b-d07842395635", 
        "prefab_sub_key": null, 
        "rotation": 0, 
        "scale": {
            "__tuple__": true, 
            "items": [
                1, 
                1
            ]
        }, 
        "scene_ui_name": null, 
        "size": {
            "__tuple__": true, 
            "items": [
                1116.0, 
                58.0
            ]
        }, 
        "swallow_touches": false, 
        "type": 7, 
        "visible": true
    }, 
    "key": "0823f4a4-d176-4dae-bb4b-d07842395635", 
    "name": "slot_main_rank"
}